sccpt/__init__.py
sccpt/capture.py
sccpt/gif.py
sccpt/utils.py
tests/__init__.py
tests/conftest.py
tests/test_sccpt.py
sccpt-0.1.0.dist-info/METADATA
sccpt-0.1.0.dist-info/WHEEL
sccpt-0.1.0.dist-info/entry_points.txt
sccpt-0.1.0.dist-info/top_level.txt
sccpt-0.1.0.dist-info/RECORD
