Metadata-Version: 2.1
Name: sccpt
Version: 0.1.0
Summary: Lightweight screen capture library optimized for WSL and Windows
Home-page: https://github.com/ywatanabe/sccpt
Author: Yusuke Watanabe
Author-email: Yusuke.Watanabe@scitex.ai
License: UNKNOWN
Keywords: screenshot screen-capture wsl windows monitoring automation
Platform: UNKNOWN
Classifier: Development Status :: 3 - Alpha
Classifier: Intended Audience :: Developers
Classifier: Topic :: Software Development :: Libraries :: Python Modules
Classifier: Topic :: Multimedia :: Graphics :: Capture :: Screen Capture
Classifier: License :: OSI Approved :: MIT License
Classifier: Programming Language :: Python :: 3
Classifier: Programming Language :: Python :: 3.7
Classifier: Programming Language :: Python :: 3.8
Classifier: Programming Language :: Python :: 3.9
Classifier: Programming Language :: Python :: 3.10
Classifier: Programming Language :: Python :: 3.11
Classifier: Operating System :: Microsoft :: Windows
Classifier: Operating System :: POSIX :: Linux
Requires-Python: >=3.7
Provides-Extra: dev
Requires-Dist: black>=22.0.0; extra == "dev"
Requires-Dist: flake8>=4.0.0; extra == "dev"
Requires-Dist: pytest>=7.0.0; extra == "dev"
Provides-Extra: full
Requires-Dist: Pillow>=9.0.0; extra == "full"
Requires-Dist: mss>=6.0.0; extra == "full"
